[
  {
    "id": 1,
    "guest_id": 1,
    "start_date": "2023-01-01",
    "end_date": "2023-01-03",
    "room_id": 1,
    "transfer_code": "hjfdjsakflhdsaklfhal"
  },
  {
    "id": 2,
    "guest_id": 1,
    "start_date": "2023-01-05",
    "end_date": "2023-01-07",
    "room_id": 1,
    "transfer_code": "djfhdajkaf"
  },
  {
    "id": 3,
    "guest_id": 1,
    "start_date": "2023-01-20",
    "end_date": "2023-01-23",
    "room_id": 1,
    "transfer_code": "lalalala"
  },
  {
    "id": 4,
    "guest_id": 1,
    "start_date": "2023-01-20",
    "end_date": "2023-01-21",
    "room_id": 1,
    "transfer_code": "fdasjklfhaskl"
  },
  {
    "id": 5,
    "guest_id": 1,
    "start_date": "2023-01-26",
    "end_date": "2023-01-28",
    "room_id": 1,
    "transfer_code": "kfjdaskfljdas"
  },
  {
    "id": 6,
    "guest_id": 1,
    "start_date": "2023-01-09",
    "end_date": "2023-01-10",
    "room_id": 1,
    "transfer_code": "381ca211-7b12-4f4f-8f52-c3732940c248&quot;"
  },
  {
    "id": 7,
    "guest_id": 1,
    "start_date": "2023-01-09",
    "end_date": "2023-01-10",
    "room_id": 1,
    "transfer_code": "381ca211-7b12-4f4f-8f52-c3732940c248&quot;"
  },
  {
    "id": 8,
    "guest_id": 1,
    "start_date": "2023-01-11",
    "end_date": "2023-01-13",
    "room_id": 1,
    "transfer_code": "d2ca0f60-3b86-48d1-bd33-b7a528752701"
  },
  {
    "id": 9,
    "guest_id": 1,
    "start_date": "2023-01-04",
    "end_date": "2023-01-04",
    "room_id": 1,
    "transfer_code": "fc222153-bed8-4210-a8e6-173d76d6045c"
  },
  {
    "id": 10,
    "guest_id": 1,
    "start_date": "2023-01-16",
    "end_date": "2023-01-16",
    "room_id": 1,
    "transfer_code": "06e9da8f-d6be-4776-8ca5-7242ed0437b5"
  },
  {
    "id": 11,
    "guest_id": 1,
    "start_date": "2023-01-17",
    "end_date": "2023-01-18",
    "room_id": 1,
    "transfer_code": "0b5888bf-a48d-47a8-bc8d-eac834edd372"
  },
  {
    "id": 12,
    "guest_id": 1,
    "start_date": "2023-01-24",
    "end_date": "2023-01-25",
    "room_id": 1,
    "transfer_code": "f147cdfd-d761-4ced-addc-1546e3e21e0b"
  },
  {
    "id": 13,
    "guest_id": 1,
    "start_date": "2023-01-19",
    "end_date": "2023-01-19",
    "room_id": 1,
    "transfer_code": "a33285cb-819d-406b-8ecf-7d79c78e0cc9"
  },
  {
    "id": 14,
    "guest_id": 8,
    "start_date": "2023-01-14",
    "end_date": "2023-01-14",
    "room_id": 1,
    "transfer_code": "95bdc91e-9ad2-4f8a-9dda-4143fe96097e"
  },
  {
    "id": 15,
    "guest_id": 9,
    "start_date": "2023-01-14",
    "end_date": "2023-01-14",
    "room_id": 1,
    "transfer_code": "8eb334fe-432e-42ed-b469-f4291db88d7f"
  },
  {
    "id": 16,
    "guest_id": 1,
    "start_date": "2023-01-29",
    "end_date": "2023-01-30",
    "room_id": 1,
    "transfer_code": "64559c67-8c83-4f93-b3f4-6343120e6ea5"
  },
  {
    "id": 17,
    "guest_id": 1,
    "start_date": "2023-01-29",
    "end_date": "2023-01-30",
    "room_id": 1,
    "transfer_code": "028e9c6f-b5aa-48f4-b0c9-a8b1631978c4"
  },
  {
    "id": 18,
    "guest_id": 1,
    "start_date": "2023-01-29",
    "end_date": "2023-01-30",
    "room_id": 1,
    "transfer_code": "353cf4c5-55c1-4781-9b5f-46b364ac761b"
  },
  {
    "id": 19,
    "guest_id": 1,
    "start_date": "2023-01-29",
    "end_date": "2023-01-30",
    "room_id": 1,
    "transfer_code": "92d2d4e2-c3a0-4502-ba59-2292754d6e09"
  },
  {
    "id": 20,
    "guest_id": 1,
    "start_date": "2023-01-08",
    "end_date": "2023-01-09",
    "room_id": 1,
    "transfer_code": "b832a352-1a17-4dd1-9879-efdab6febb36"
  },
  {
    "id": 21,
    "guest_id": 1,
    "start_date": "2023-01-08",
    "end_date": "2023-01-09",
    "room_id": 1,
    "transfer_code": "3c5bab00-a1f1-4bb9-a3dc-3dfbcc4b935f"
  }
]
